Workbook

Sheet Resumo 
A1: Nº | B1: FORNECEDOR | C1: VALOR ORÇAMENTO | D1: FORMA DE PAGAMENTO | E1: LOCAL DE ENTREGA | F1: DADOS DE PAGAMENTO | G1: STATUS DA COMPRA | H1: NOTA FISCAL
A2: 1 | B2: CELMAT | C2: =SUMIF('Tabela padrão - Suprimentos méd'!#REF!,'Resumo '!B2,'Tabela padrão - Suprimentos méd'!#REF!) -> #REF! | D2: À VISTA | E2: STRALOG | F2: Banco Bradesco Ag. 0287 C/C 4553-5 VAD MEDICAL | G2: REALIZAR PAGAMENTO
A3: 2 | B3: CIRURGICA ESTILO | C3: =SUMIF('Tabela padrão - Suprimentos méd'!#REF!,'Resumo '!B3,'Tabela padrão - Suprimentos méd'!#REF!) -> #REF! | D3: CARTÃO DE CRÉDITO | E3: ESCRITÓRIO | F3: CARTÃO DE CRÉDITO | G3: NF | H3: 3596
A4: 3 | B4: CIRURGICA ATLANTICA | C4: =SUMIF('Tabela padrão - Suprimentos méd'!#REF!,'Resumo '!B4,'Tabela padrão - Suprimentos méd'!#REF!) -> #REF! | D4: À VISTA | E4: STRALOG | F4: PIX: 55.666.777/0001-81 CIRURGICA ATLANTICA C.MAT.CIR.HO.SO. LTDA | G4: NF | H4: 1437267
A5: 4 | B5: CIRURGICA PASSOS | C5: =SUMIF('Tabela padrão - Suprimentos méd'!#REF!,'Resumo '!B5,'Tabela padrão - Suprimentos méd'!#REF!) -> #REF! | D5: À VISTA | E5: STRALOG | G5: REALIZAR PAGAMENTO
A6: 5 | B6: CLARAMED | C6: =SUMIF('Tabela padrão - Suprimentos méd'!#REF!,'Resumo '!B6,'Tabela padrão - Suprimentos méd'!#REF!) -> #REF! | D6: À VISTA | E6: STRALOG | F6: Banco Santander Agencia 4628 C/c 13003351-0 Cnpj :99.000.111/0001-65 | G6: REALIZAR PAGAMENTO
A7: 6 | B7: FIBRA CIRÚRGICA | C7: =SUMIF('Tabela padrão - Suprimentos méd'!#REF!,'Resumo '!B7,'Tabela padrão - Suprimentos méd'!#REF!) -> #REF! | D7: CARTÃO DE CRÉDITO | E7: STRALOG | F7: CARTÃO DE CRÉDITO | G7: COMPRADO SITE | H7: 469301
A8: 7 | B8: HOSPITALAR | C8: =SUMIF('Tabela padrão - Suprimentos méd'!#REF!,'Resumo '!B8,'Tabela padrão - Suprimentos méd'!#REF!) -> #REF! | G8: Não é possivel mais realizar compras
A9: 8 | B9: KALUNGA | C9: =SUMIF('Tabela padrão - Suprimentos méd'!#REF!,'Resumo '!B9,'Tabela padrão - Suprimentos méd'!#REF!) -> #REF! | D9: CARTÃO DE CRÉDITO | E9: ESCRITÓRIO | F9: CARTÃO DE CRÉDITO | G9: COMPRADO SITE
A10: 9 | B10: MAGAZINE MÉDICA | C10: =SUMIF('Tabela padrão - Suprimentos méd'!#REF!,'Resumo '!B10,'Tabela padrão - Suprimentos méd'!#REF!) -> #REF! | D10: CARTÃO DE CRÉDITO | E10: STRALOG | F10: CARTÃO DE CRÉDITO | G10: COMPRADO SITE
A11: 10 | B11: MNP | C11: =SUMIF('Tabela padrão - Suprimentos méd'!#REF!,'Resumo '!B11,'Tabela padrão - Suprimentos méd'!#REF!) -> #REF! | D11: À VISTA | E11: STRALOG | F11: Banco: Bradesco 7808-5 Conta corrente. 0008367-4 CNPJ 88.999.000/0001-98 | G11: REALIZAR PAGAMENTO
A12: 11 | B12: NEWMED | C12: =SUMIF('Tabela padrão - Suprimentos méd'!#REF!,'Resumo '!B12,'Tabela padrão - Suprimentos méd'!#REF!) -> #REF! | D12: À VISTA | E12: STRALOG | F12: NEWMED PRODUTOS PARA SAUDE LTDA - PIX CNPJ: 1aeb7ac5-8299-42fb-aad3-89bfb82ef807 | G12: REALIZAR PAGAMENTO
A13: 12 | B13: PRODUTOS HOSPITALARES ONLINE | C13: =SUMIF('Tabela padrão - Suprimentos méd'!#REF!,'Resumo '!B13,'Tabela padrão - Suprimentos méd'!#REF!) -> #REF! | D13: CARTÃO DE CRÉDITO | E13: STRALOG | F13: CARTÃO DE CRÉDITO | G13: COMPRADO SITE
A14: 13 | B14: SUPER EPI | C14: =SUMIF('Tabela padrão - Suprimentos méd'!#REF!,'Resumo '!B14,'Tabela padrão - Suprimentos méd'!#REF!) -> #REF! | D14: CARTÃO DE CRÉDITO | E14: ESCRITÓRIO | F14: CARTÃO DE CRÉDITO | G14: NF | H14: 125870
A15: 14 | B15: MEDSUL | C15: 15051.35 | D15: À VISTA | E15: STRALOG | F15: CNPJ: 11222333000181 | G15: REALIZAR PAGAMENTO
A16: 15 | B16: UTILIDADES MÉDICAS | C16: =SUMIF('Tabela padrão - Suprimentos méd'!#REF!,'Resumo '!B16,'Tabela padrão - Suprimentos méd'!#REF!) -> #REF! | D16: CARTÃO DE CRÉDITO | E16: ESCRITÓRIO | F16: CARTÃO DE CRÉDITO | G16: NF | H16: 4180749
A17: 16 | B17: VERBENNA | C17: =SUMIF('Tabela padrão - Suprimentos méd'!#REF!,'Resumo '!B17,'Tabela padrão - Suprimentos méd'!#REF!) -> #REF! | D17: À VISTA | E17: ESCRITÓRIO
A18: 17 | B18: Newvita | C18: =SUMIF('Tabela padrão - Suprimentos méd'!#REF!,'Resumo '!B18,'Tabela padrão - Suprimentos méd'!#REF!) -> #REF! | D18: CARTÃO DE CRÉDITO | E18: STRALOG | F18: CARTÃO DE CRÉDITO | G18: COMPRADO SITE
B19: VALOR TOTAL | C19: =SUM(C2:C18) -> #REF!

Sheet Tabela padrão - Suprimentos méd
A1: DESCRIÇÃO | B1: QUANTIDADE | C1: OBSERVAÇÃO | D1: NCM | E1: UNIDADE DE MEDIDA | F1: Classificação | G1: SETOR
A2: ABAIXADOR DE LINGUA INFANTL | B2: 2 | C2: COMPRAR NO LOCAL | D2: 90189099 | E2: PACOTE | F2: Itens cirúrgicos | G2: TRIAGEM - PEDIATRIA
A3: ABAIXADOR DE LINGUA MADEIRA PCT C/100 | B3: 10 | C3: COMPRAR NO LOCAL | D3: 90189099 | E3: PACOTE | F3: Itens cirúrgicos | G3: TRIAGEM/ PRÉ E PÓS
A4: ALCOOL 70% | B4: 10 | C4: COMPRAR NO LOCAL
A5: ALCOOL EM GEL - 500ML | B5: 20 | C5: COMPRAR NO LOCAL
A6: ÁCIDO TRANEXÂMICO 5ML | B6: 60 | C6: Considerar 1 ampola por paciente | D6: 90189010 | E6: UNIDADE | F6: Medicamento | G6: ANESTESIA - MEDICAMENTOS
A7: ADAPTADOR VACUNTAINER PARA COLETA DE SANGUE A VACUO | B7: 4 | C7: Pedir para o hospital | D7: 90183119 | E7: UNIDADE | F7: Itens cirúrgicos | G7: Triagem - Coleta de sangue
A8: ADENOSINA 3MG/ML - AMPOLA 2ML -SOLUCAO INJETAVEL | B8: 10 | D8: 29349129 | E8: UNIDADE | F8: Medicamento | G8: ANESTESIA - MEDICAMENTOS
A9: ADESIVO DERMABOND 5 ML | B9: 5 | C9: DOAÇÃO J&J | D9: 30061090 | E9: CAIXA | F9: Itens cirúrgicos | G9: FIO DE SUTURA
A10: ADRENALINA 1MG/ML AMPOLA 1ML SOLUCAO INJETAVEL | B10: 100 | D10: 30049021 | E10: UNIDADE | F10: Medicamento | G10: ANESTESIA - MEDICAMENTOS
A11: AGUA DESTILADA PARA INJEÇÃO - AMPOLA 10ML - SOLUÇÃ+A1:P376O INJETÁVEL | B11: 100 | D11: 30049099 | E11: UNIDADE | F11: Medicamento | G11: ANESTESIA - MEDICAMENTOS
A12: AGULHA HIPODERMICA DESCARTAVEL 21GX1.1/2 (40X08) | B12: 300 | D12: 90183219 | E12: UNIDADE | F12: Itens cirúrgicos | G12: OR
A13: AGULHA HIPODERMICA DESCARTAVEL 18GX1.1/2 (40X12) | B13: 300 | D13: 90183219 | E13: UNIDADE | F13: Itens cirúrgicos | G13: OR
A14: AGULHA HIPODERMICA DESCARTAVEL 19G 1.1 (30X10) | B14: 300 | D14: 90183219 | E14: UNIDADE | F14: Itens cirúrgicos | G14: OR
A15: AGULHA HIPODERMICA DESCARTAVEL 23GX1(25X6) | B15: 300 | D15: 90183219 | E15: UNIDADE | F15: Itens cirúrgicos | G15: OR
A16: AGULHA HIPODERMICA DESCARTAVEL 25G X 5/8" (25X08) | B16: 200 | D16: 90183219 | E16: UNIDADE | F16: Itens cirúrgicos | G16: OR
A17: ALMOFADA PARA ASSEPSSIA COM ALCOOL 70% (ALCOHOL SWAB SACHE) - CAIXA C/ 200 SACHES | B17: 5 | C17: COMPRAR NO LOCAL | D17: 30059090 | E17: UNIDADE | F17: Itens cirúrgicos | G17: OR
A18: AMINOFILINA 250 MG (25MG/ML) - AMPOLA 10 ML - SOLUÇÃO INJETÁVEL | B18: 3 | D18: 30049099 | E18: UNIDADE | F18: Medicamento | G18: ANESTESIA - MEDICAMENTOS
A19: AMOXICILINA 250MG/5ML-SUPENSAO ORAL-FRASCO | B19: 50 | C19: Comprar no local - Após reunião de Team Leaders | D19: 30049099 | E19: UNIDADE | F19: Medicamento | G19: PRÉ E PÓS
A20: ASPIRADOR CIRURGICO C/EXTENSAO 3.0 METROS-CANULA YANKAUER | B20: 80 | C20: 1 por paciente | D20: 90183929 | E20: UNIDADE | F20: Itens cirúrgicos | G20: KIT BASICO POR CIRURGIA
A21: AVENTAL CIRURGICO DES ESTERIL TAM EXTRA GRANDE | B21: =4*62 -> 248 | C21: 3 por paciente (CP full+CP OBS+Instrumentador) | D21: 62101000 | E21: UNIDADE | F21: Itens cirúrgicos | G21: KIT BASICO POR CIRURGIA
A22: AZITROMICINA 500 MG - COMPRIMIDOS | B22: 10 | C22: COMPRAR NO LOCAL | D22: 30042029 | E22: UNIDADE | F22: Medicamento | G22: PRÉ E PÓS/ KIT DO TIME
A23: AZITROMICINA DI-HIDRATADA 500MG - PÓ LIOFILIZADO P/ INFUSÃO - SOLUÇÃO INJETÁVEL | B23: 5 | C23: DOAÇÃO CRISTÁLIA | D23: 30042029 | E23: UNIDADE | F23: Itens cirúrgicos | G23: ANESTESIA - MEDICAMENTOS
A24: AZUL DE METILENO 1% - AMPOLA 2ML - SOLUCAO ESTERIL | B24: 20 | D24: 29343090 | E24: UNIDADE | F24: Medicamento | G24: OR
A25: BROMETO DE IPRATRÓPIO 0,25MG/ML - FRASCO 20ML | B25: 3 | C25: COMPRAR NO LOCAL | D25: 30049099 | E25: UNIDADE | F25: Medicamento | G25: PRÉ E PÓS/RECUPERAÇÃO
A26: BROMETO DE ROCURÔNIO 10MG/ML - FRASCO 5ML - SOLUÇÃO INJETÁVEL | B26: 15 | C26: DOAÇÃO CRISTÁLIA | D26: 30049099 | E26: UNIDADE | F26: Itens cirúrgicos | G26: ANESTESIA - MEDICAMENTOS
A27: BROMIDRATO DE FENOTEROL 100MCG 10ML AEROSOL | B27: 2 | C27: COMPRAR NO LOCAL | D27: 30049039 | E27: UNIDADE | F27: Medicamento | G27: PRÉ E PÓS/RECUPERAÇÃO
A28: BROMIDRATO DE FENOTEROL 5MG/ML - SOLUÇÃO PARA NEBULIZAÇÃO | B28: 2 | C28: COMPRAR NO LOCAL | D28: 30049039 | E28: UNIDADE | F28: Medicamento | G28: PRÉ E PÓS/RECUPERAÇÃO
A29: BUPIVACAÍNA 25% - COM ADRENALINA - AMPOLA 50ML 1:200,000 - SOLUÇÃO INJETÁVEL | B29: 20 | C29: DOAÇÃO CRISTÁLIA | G29: ANESTESIA - MEDICAMENTOS
A30: BUPIVACAÍNA 0.5% - SEM ADRENALINA - AMPOLA 20ML - SOLUÇÃO INJETÁVEL | B30: 50 | C30: DOAÇÃO CRISTÁLIA | D30: 30049061 | E30: UNIDADE | F30: Itens cirúrgicos | G30: ANESTESIA - MEDICAMENTOS
A31: CAMPO CIRURGICO DESCARTAVEL ESTERIL 1.50M X 2.20M ( | B31: 80 | C31: 1 por paciente | D31: 30059020 | E31: UNIDADE | F31: Itens cirúrgicos | G31: KIT BASICO POR CIRURGIA
A32: CAMPO CIRURGICO DESCARTAVEL ESTERIL 1.50M X 1.50M | B32: 80 | C32: 1 por paciente | D32: 30059020 | E32: UNIDADE | F32: Itens cirúrgicos | G32: KIT BASICO POR CIRURGIA
A33: CAMPO PARA MESA DE MAYO ESTERIL 60 CM X 1.40 MT | B33: 70 | C33: 1 por paciente | D33: 30059020 | E33: UNIDADE | F33: Itens cirúrgicos | G33: KIT BASICO POR CIRURGIA
A34: CANETA PARA ELETROCAUTERIO DESCARTAVEL | B34: 70 | C34: 1 por paciente | D34: 90181490 | E34: UNIDADE | F34: Itens cirúrgicos | G34: KIT BASICO POR CIRURGIA
A35: CANULA DE GUEDEL 50MM NR. 0 | B35: 20 | D35: 90183929 | E35: UNIDADE | F35: Itens cirúrgicos | G35: ANESTESIA
A36: CANULA NASOFARINGEA 12FR - 4.0 MM | B36: 8 | D36: 90183929 | E36: UNIDADE | F36: Itens cirúrgicos | G36: ANESTESIA
A37: CANULA NASOFARINGEA 14FR - 4.5 MM | B37: 8 | D37: 90183929 | E37: UNIDADE | F37: Itens cirúrgicos | G37: ANESTESIA
A38: CANULA NASOFARINGEA 16FR - 5.5 MM | B38: 8 | D38: 90183929 | E38: UNIDADE | F38: Itens cirúrgicos | G38: ANESTESIA
A39: CANULA NASOFARINGEA 18FR | B39: 8
A40: CÂNULA NASOFARÍNGEA 28FR
A41: CÂNULA NASOFARÍNGEA 24FR
A42: CÂNULA NASOFARÍNGEA 22FR
A43: CANULA NASOFARINGEA 20FR - 6.5 MM | B43: 8 | D43: 90183929 | E43: UNIDADE | F43: Itens cirúrgicos | G43: ANESTESIA
A44: CATETER INTRAVENOSO COM AGULHA 16 GA | B44: 20 | D44: 90183929 | E44: UNIDADE | F44: Itens cirúrgicos | G44: ANESTESIA
A45: CATETER INTRAVENOSO COM AGULHA 18 GA | B45: 20 | D45: 90183929 | E45: UNIDADE | F45: Itens cirúrgicos | G45: ANESTESIA
A46: CEFAZOLINA 1GR - PÓ PARA SOLUÇÃO INJETÁVEL | B46: 150 | D46: 30042051 | E46: UNIDADE | F46: Medicamento | G46: ANESTESIA - MEDICAMENTOS
A47: CETOROLACO DE TROMETAMINA 30MG/ML | B47: 30 | D47: 30049099 | E47: UNIDADE | F47: Medicamento | G47: ANESTESIA - MEDICAMENTOS
A48: CIRCUITO DE ANESTESIA 1 L | B48: 10 | G48: ANESTESIA
A49: CIRCUITO DE ANESTESIA 2 L | B49: 10 | G49: ANESTESIA
A50: CO2 Detector Adult Easy Cap II | B50: 6 | C50: OSI | G50: CRASHBOX/PACUBOX/DAB
A51: CO2 Detector Pediatric Pedi-Cap 24/bx | B51: 6 | C51: OSI | G51: CRASHBOX/PACUBOX/DAB
A52: CLORETO DE CÁLCIO 10% - 100 MG/ML - AMPOLA 10 ML | B52: 10 | C52: Pedir para o hospital | D52: 28272090 | E52: UNIDADE | F52: Medicamento | G52: CRASHBOX/PACUBOX/DAB
A53: CLORETO DE SUXAMETÔNIO 100 MG - PÓ PARA SOLUÇÃO INJETÁVEL - SUCCINIL | B53: 20 | D53: 30049099 | E53: UNIDADE | F53: Medicamento | G53: ANESTESIA - MEDICAMENTOS
A54: CLOREXIDINA 2% - SOLUÇÃO DEGERMANTE ALCOOLICA - FRASCO 100 ML | B54: 12 | D54: 30012090 | E54: UNIDADE | F54: Medicamento | G54: ANESTESIA - MEDICAMENTOS
A55: CLORIDRATO DE PROMETAZINA 50MG/ML -AMPOLA 2ML -SOLUCAO INJETAVEL | B55: 20 | D55: 30042099 | E55: UNIDADE | F55: Medicamento | G55: ANESTESIA - MEDICAMENTOS
A56: CLORIDRATO DE CLONIDINA - SOLUÇÃO INJETÁVEL 150MCG/ML - AMPOLA 1 ML | B56: 15 | C56: DOAÇÃO CRISTÁLIA | D56: 30049039 | E56: UNIDADE | F56: Itens cirúrgicos | G56: ANESTESIA - MEDICAMENTOS
A57: CLORIDRATO DE DEXTROCETAMINA 50 MG/ML - AMPOLA 02ML | B57: 20 | C57: DOAÇÃO CRISTÁLIA | D57: 30049032 | E57: UNIDADE | F57: Itens cirúrgicos | G57: ANESTESIA - MEDICAMENTOS
A58: CLORIDRATO DE DOPAMINA 5MG/ML - AMPOLA 5 ML - SOLUÇÃO INJETÁVEL | B58: 14 | C58: DOAÇÃO CRISTÁLIA | D58: 30049039 | E58: UNIDADE | F58: Itens cirúrgicos | G58: ANESTESIA - MEDICAMENTOS
A59: CLORIDRATO DE ESMOLOL 10MG/ML - AMPOLA 1ML - SOLUÇÃO INJETÁVEL | B59: 5 | C59: DOAÇÃO CRISTÁLIA | D59: 30049039 | E59: UNIDADE | F59: Itens cirúrgicos | G59: ANESTESIA - MEDICAMENTOS
A60: Cloridrato de Fenilefrina 1ML | B60: 2 | C60: DOAÇÃO CRISTÁLIA | G60: ANESTESIA - MEDICAMENTOS
A61: CLORIDRATO DE ETILEFRINA - 10MG/ML - AMPOLA 1ML | B61: 4 | C61: DOAÇÃO CRISTÁLIA | D61: 30042099 | E61: UNIDADE | F61: Medicamento | G61: ANESTESIA - MEDICAMENTOS
A62: CLORIDRATO DE LIDOCAINA 2% 20 MG/ML - SOLUÇÃO INJETÁVEL | B62: 50 | C62: DOAÇÃO CRISTÁLIA | D62: 30049099 | E62: UNIDADE | F62: Itens cirúrgicos | G62: ANESTESIA - MEDICAMENTOS
A63: CLORIDRATO DE LIDOCAÍNA 2% - GELÉIA ESTÉRIL - BISNAGA 30GR | B63: 3 | C63: DOAÇÃO CRISTÁLIA | D63: 30049099 | E63: UNIDADE | F63: Itens cirúrgicos | G63: ANESTESIA - MEDICAMENTOS
A64: CLORIDRATO DE NALBUFINA 10MG/ML - AMPOLA 10ML - SOLUÇÃO INJETÁVEL | B64: 20 | C64: DOAÇÃO CRISTÁLIA | D64: 30049039 | E64: UNIDADE | F64: Itens cirúrgicos | G64: ANESTESIA - MEDICAMENTOS
A65: CLORIDRATO DE NALOXONA 0.4 MG/ML - AMPOLA 2ML - SOLUÇÃO INJETÁVEL | B65: 20 | C65: DOAÇÃO CRISTÁLIA | D65: 30049069 | E65: UNIDADE | F65: Itens cirúrgicos | G65: ANESTESIA - MEDICAMENTOS
A66: CLORIDRATO DE ONDANSETRONA 4MG/ML 2ML | B66: 25 | C66: DOAÇÃO CRISTÁLIA | D66: 30049099 | E66: UNIDADE | F66: Medicamento | G66: ANESTESIA - MEDICAMENTOS
A67: COLETOR DE SECRECOES 3.500ML-NAO ESTERIL | B67: 10 | D67: 90183929 | E67: UNIDADE | F67: Itens cirúrgicos | G67: OR
A68: COLETOR PERFURO CORTANTE 07 LITROS | B68: 7 | C68: COMPRAR NO LOCAL | D68: 48191000 | E68: UNIDADE | F68: Itens cirúrgicos | G68: OR/PRÉ E PÓS/RECUPERAÇÃO
A69: COMPRESSA DE GAZE HIDROFILA 7.5CM X 7.5CM-PCT C/500 | B69: 5 | D69: 30059090 | E69: UNIDADE | F69: Itens cirúrgicos | G69: PRÉ E PÓS/RECUPERAÇÃO
A70: COMPRESSA DE GAZE RADIOPACA ESTERIL 7.5 CM X 7.5 CM 13 FIOS - ENVELOPE C/ 02 UNID. | B70: 50 | D70: 30059090 | E70: UNIDADE | F70: Itens cirúrgicos | G70: OR
A71: CONECTOR EM “T DE AYRES” ADICIONAL DE GASES INF.PARA BARAKA | B71: 10 | D71: 90192010 | E71: UNIDADE | F71: Itens cirúrgicos | G71: ANESTESIA
A72: CONECTOR PSU GIRAT ANG SEM ABERTURA | B72: 2 | D72: 39174090 | E72: UNIDADE | F72: Itens cirúrgicos | G72: ANESTESIA
A73: CONECTOR UNIAO RETO 1/4X1/4 | B73: 10 | D73: 39174090 | E73: UNIDADE | F73: Itens cirúrgicos | G73: ANESTESIA
A74: COPO PLASTICO DESCARTAVEL 50ML - PACOTE C/100 UNID | B74: 1 | C74: COMPRAR NO LOCAL | D74: 39232190 | E74: UNIDADE | F74: Ativo fixo
A75: CURATIVO ADESIVO | B75: 5 | C75: COMPRAR NO LOCAL | D75: 30059090 | E75: UNIDADE | F75: Itens cirúrgicos | G75: PRÉ E PÓS
A76: CURATIVO PÓS PUNÇÃO (BLOOD STOP) - CAIXA C/ 500 UNIDADES | B76: 1 | C76: COMPRAR NO LOCAL | D76: 30059090 | E76: UNIDADE | F76: Itens cirúrgicos | G76: Triagem - Coleta de sangue
A77: DEXAMETASONA 4MG/ML-AMPOLA 2,5 ML-SOLUCAO INJETAVEL | B77: 30 | D77: 29372210 | E77: UNIDADE | F77: Medicamento | G77: ANESTESIA - MEDICAMENTOS
A78: DIFENIL-HIDANTOÍNA 50MG/ML - AMPOLA 5ML - SOLUÇÃO INJETÁVEL | B78: 2 | C78: DOAÇÃO CRISTÁLIA | D78: 30049032 | E78: UNIDADE | F78: Itens cirúrgicos | G78: ANESTESIA - MEDICAMENTOS
A79: DIPIRONA 500MG - COMPRIMIDO | B79: 2 | C79: COMPRAR NO LOCAL | D79: 30039099 | E79: UNIDADE | F79: Medicamento | G79: KIT DO TIME/PRÉ E PÓS
A80: DIPIRONA MONOHIDRATADA 500 MG/ ML | B80: 2 | C80: COMPRAR NO LOCAL | D80: 30039099 | E80: UNIDADE | F80: Medicamento | G80: KIT DO TIME/PRÉ E PÓS
A81: DRENO DE PENROSE TAM 1 (11MMX6MMX30CM) | B81: 3 | D81: 90183921 | E81: UNIDADE | F81: Itens cirúrgicos | G81: OR
A82: EFEDRINA 50MG/ML - AMPOLA 1ML - SOLUÇÃO INJETÁVEL | B82: 12 | D82: 30044100 | E82: UNIDADE | F82: Itens cirúrgicos | G82: ANESTESIA - MEDICAMENTOS
A83: ELETRODO UNIVERSAL | B83: 300 | D83: 90189099 | E83: UNIDADE | F83: Itens cirúrgicos | G83: OR
A84: ENVELOPE P/ ESTERILIZACAO C/ AUTOSELANTE-250MMX380MM | B84: 50 | D84: 48189090 | E84: UNIDADE | F84: Itens cirúrgicos | G84: OR
A85: EQUIPO COM CAMARA GRADUADA (BURETA)150 ML | B85: 70 | C85: 1 por paciente | D85: 90189010 | E85: UNIDADE | F85: Itens cirúrgicos | G85: ANESTESIA
A86: EQUIPO INFUSOR 02 VIAS C/ PINCA CORTA FLUXO | B86: 70 | C86: 1 por paciente | D86: 90189010 | E86: UNIDADE | F86: Itens cirúrgicos | G86: ANESTESIA
A87: EQUIPO MACROGOTAS COM INJETOR LATERAL
A88: EQUIPO MICROGOTAS COM INJETOR LATERAL | B88: 80 | D88: 90189010 | E88: UNIDADE | F88: Itens cirúrgicos | G88: ANESTESIA
A89: ESPARADRAPO IMPERMEAVEL 100 MM X 4.5 MT | B89: 20 | C89: COMPRAR NO LOCAL | D89: 30051090 | E89: UNIDADE | F89: Itens cirúrgicos | G89: OR
A90: ESPARADRAPO IMPERMEAVEL 25MM X 4.5 | B90: 20 | C90: COMPRAR NO LOCAL | D90: 30051090 | E90: UNIDADE | F90: Itens cirúrgicos | G90: OR
A91: ETOMIDATO 2MG/ML -AMPOLA 10 ML -SOLUCA INJETAVEL | B91: 4 | C91: DOAÇÃO CRISTÁLIA | D91: 30049039 | E91: UNIDADE | F91: Medicamento | G91: ANESTESIA - MEDICAMENTOS
A92: EXTENSÃO PARA ASPIRAÇÃO CIRURGICA 4.0 METROS | B92: 25 | D92: 90183929 | E92: UNIDADE | F92: Itens cirúrgicos | G92: KIT BASICO POR CIRURGIA
A93: FENTANIL 50 MCG/ML - AMPOLA 02 ML - SOLUÇÃO INJETÁVEL | B93: 50 | C93: DOAÇÃO CRISTÁLIA | D93: 30049099 | E93: UNIDADE | F93: Itens cirúrgicos | G93: ANESTESIA - MEDICAMENTOS
A94: FILTRO BARREIRA ANESTESIA - TAM. ADULTO | B94: 50 | C94: 1 por paciente | D94: 90189099 | E94: UNIDADE | F94: Itens cirúrgicos | G94: ANESTESIA
A95: FILTRO BARREIRA ANESTESIA - TAM. PEDIÁTRICO | B95: 70 | C95: 1 por paciente | D95: 90189099 | E95: UNIDADE | F95: Itens cirúrgicos | G95: ANESTESIA
A96: FIO DE SUTURA 2-0 SEDA AGULHA FS | B96: 1 | C96: DOAÇÃO J&J | D96: 30061090 | E96: CAIXA | F96: Itens cirúrgicos | G96: FIO DE SUTURA
A97: FIO DE SUTURA 3-0 SEDA AGULHA FS | B97: 1 | C97: DOAÇÃO J&J | D97: 30061090 | E97: CAIXA | F97: Itens cirúrgicos | G97: FIO DE SUTURA
A98: FIO DE SUTURA 4-0 MONOCRYL AGULHA P-3 | B98: 1 | C98: DOAÇÃO J&J | D98: 30061090 | E98: CAIXA | F98: Itens cirúrgicos | G98: FIO DE SUTURA
A99: FIO DE SUTURA 4-0 MONOCRYL AGULHA PS-2 | B99: 1 | C99: DOAÇÃO J&J | D99: 30061090 | E99: CAIXA | F99: Itens cirúrgicos | G99: FIO DE SUTURA
A100: FIO DE SUTURA 4-0 MONOCRYL AGULHA PS-4 | B100: 1 | C100: DOAÇÃO J&J | D100: 30061090 | E100: CAIXA | F100: Itens cirúrgicos | G100: FIO DE SUTURA
...

Sheet Planilha1
B3: Medicações | C3: Lote | D3: Vencimento | E3: Coluna3 | F3: Quantidade | G3: Necessario | H3: Caixa
B4: XYLESTESIN CLORIDRATO DE LIDOCAÍNA 2,0% 20MG/ML 20ML | C4: 50018091 | D4: 46054 | E4: UN | F4: 16 | H4: DAB 01
B5: XYLESTESIN LIDOCAÍNA 10% 100MG/ML - 50ML | C5: 50020182 | D5: 46691 | E5: UN | F5: 1 | H5: DAB 01
B6: DANTROLEN IV DANTROLENO SÓDICO 20MG | C6: 50022375 | D6: 46752 | E6: - | F6: 3 | H6: OR 06
B7: DANTROLEN IV DANTROLENO SÓDICO 20MG | C7: - | D7: - | E7: UN | F7: 3 | H7: AN 20
B8: SULFATO DE TERBUTALINA 0,5 MG - 1 ML | C8: 2515166 | D8: 46569 | E8: UN | F8: 4 | H8: OR 11
B9: AEROFIN SPRAY - SALBUTAMOL 100 MCG/DOSE 200 DOSES | C9: 2425211 | D9: 46356 | E9: UN | F9: 1 | H9: OR 11
B10: NARIDRIN - CLORIDRATO DE NAFAZOLINA + MALEATO DE MEPIRAMINA + DEXPANTENOL 1MG/ML + 0,2MG/ML + 5MG/ML | C10: 4N5849 | D10: 46784 | E10: UN | F10: 1 | H10: OR 11
B11: ETILEFRIL CLOR. DE ETILEDFRINA 10MG/ML 1ML ADUL/PED | C11: 2448216 | D11: 46357 | E11: UN | F11: 12 | H11: DAB 01
B12: SUCCITRAT - CLORE. DE SUXAMETÔNIO 100MG | C12: 24070177 | D12: 46174 | E12: UN | F12: 10 | H12: DAB 01
B13: FOSFATO SÓDICO DE DEXAMETASONA 4MG/ML IV/IM | C13: DX25B025 | D13: 46388 | E13: UN | F13: =1+19 -> 20 | H13: DAB 01 / AN 15
B14: BRIDION 200 MG/ML - 2ML | C14: A102959 | D14: 46023 | E14: UN | F14: 1 | H14: DAB 01
B15: FENILEFRIN - CLORIDRATO DE FENILEFRINA 10MG/ML - 1ML | C15: 50014479 | D15: 46143 | E15: UN | F15: 20 | H15: DAB 01
B16: PARINEX - HEPARINA SÓDICA SUÍNA - 5ML | C16: U027/25 | D16: 46266 | E16: UN | F16: 20 | H16: DAB 01
B17: TROMETAMOL CETOROLACO 30MG/ML - 1ML I.M./I.V. | C17: BH-007/24 | D17: 46235 | E17: UN | F17: 9 | H17: DAB 01
B18: NORMASTIG METILSULFATO DE NEOSTIGMINA 0,5MG/ML | C18: 2523019H | D18: 46508 | E18: UN | F18: 20 | H18: DAB 01
B19: CEFAZOLINA SÓDICA 1MG VIA INTRAVENOSA | C19: 10577 | D19: 46419 | E19: UN | F19: 12 | H19: DAB 01
B20: SULFATO DE TERBUTALINA 0,5 MG - 1 ML | C20: AV-002/25 | D20: 46447 | E20: UN | F20: 49 | H20: DAB 01
B21: FUROSEMIDA 10MG/ML - 2ML | C21: 25050480 | D21: 46508 | E21: UN | F21: =3+50 -> 53 | H21: DAB 01 / AN 15
B22: CLORID. DE AMIODARONA 50MG/ML - 3ML | C22: AD-027/24 | D22: 46296 | E22: UN | F22: 45 | H22: DAB 01
B23: DIFENIDRIN CLORID. DE DIFENIDRAMINA 50MG/ML - 1 ML | C23: 50025174 | D23: 46784 | E23: UN | F23: 12 | H23: DAB 01
B24: UNIFEDRINE 50MG/ML - SULFATO DE EFEDRINA - 1 ML | C24: 2432348.A | D24: 46235 | E24: UN | F24: 12 | H24: DAB 01
B25: CLORID. DE ONDANSETRONA 2MG/ML - 2ML | C25: 5030150 | D25: 46447 | E25: UN | F25: 12 | H25: DAB 01
B26: CLORID. DE NAXOLONA 0,4MG/ML - 1 ML | C26: BA006/24 | D26: 46204 | E26: UN | F26: 22 | H26: DAB 01
B27: CLONIDIN CLORID. DE CLONIDINA 150 MCG/ML - 1ML | C27: 50023052 | D27: 46357 | E27: UN | F27: 13 | H27: DAB 01
B28: NEOCAÍNA - CLORIDRATO DE BUPIVACAÍNA 0,50% 5MG/ML 20ML - S/ VASO CONSTRITOR | C28: 50024029 | D28: 46753 | E28: UN | F28: 3 | H28: DAB 01
B29: SULFATO DE ATROPINA 0,25 MG/ML IV/IM/SC | C29: AT24L030 | D29: 46296 | E29: UN | F29: 33 | H29: AN 15
B30: ETOMIDATO 2MG/ML - 10 ML | C30: 50024334 | D30: 46419 | E30: UN | F30: 44 | H30: AN 15
B31: PROPOFOL 10MG/ML ADUL/PED. - 20ML | C31: AOHO702A | D31: 46356 | E31: UN | F31: 9 | H31: AN 15
B32: MIDAZOLAM 5MG/ML IV/IM | C32: AP-025/25 | D32: 46419 | E32: UN | F32: 43 | H32: AN 15
B33: ÁCIDO TRANEXÂMICO 50MG/ML - 5ML | C33: BD-015/25 | D33: 46388 | E33: UN | F33: =1+34 -> 35 | H33: AN 15
B34: NUBAIN CLORID. DE NALBUFINA 10MG/ML - 1 ML | C34: 50021506 | D34: 46692 | E34: UN | F34: 10 | H34: AN 15
B35: FLUMAZENIL 0,1 MG/ML - 5 ML | C35: BF-002/25 | D35: 46266 | E35: UN | F35: 15 | H35: AN 15
B36: KETAMIN NP CLORID. DE ESCETAMINA 50MG/ML - 2 ML | C36: 50025872 | D36: 46447 | E36: UN | F36: 9 | H36: AN 15
B37: PAMERGAN CLORID. DE PROMETAZINA 25MG/ML - 2 ML | C37: 50028182 | D37: 46508 | E37: UN | F37: 15 | H37: AN 15
B38: CITRATO DE FENTANILA 50MGC/ML - 2 ML EPI-IV-IM | C38: AS-047/25M | D38: 46447 | E38: UN | F38: 10 | H38: AN 15
B39: ADENOSINA 3MG/ML I.V. - 2 ML | C39: BC-013/24M | D39: 46296 | E39: UN | F39: 17 | H39: AN 15
B40: SUCCINATO SÓDICO DE HIDROCORTISONA 500MG EM PÓ INJETÁVEL | C40: 25060122 | D40: 46508 | E40: UN | F40: 20 | H40: AN 15
B41: ENCRISE - VASOPRESSINA 20 U/ML - AMP. DE 1 ML | C41: 40709684 | D41: 46326 | E41: UN | F41: 10 | H41: AN 15
B42: AMINOFILINA 24MG/ML - AMP. 10 ML | C42: E-008/24M | D42: 46143 | E42: UN | F42: 100 | H42: AN 15
B43: NEOCAINA 5 MG | C43: 50017721 | D43: 46054 | E43: CX | F43: 3 | H43: OR 92
B44: NEOCAINA 5 MG | C44: 50024029 | D44: 46753 | E44: CX | F44: 1 | H44: OR 92
B45: SUCCINIL 100 MG | C45: 2448593 | D45: 46357 | E45: CX | F45: 2 | H45: OR 92
B46: CLORETO DE CALCIO 10% | C46: 25050039 | D46: 46514 | E46: CX | F46: 1 | H46: OR 92
B47: XYLESTESIN 20 MG | C47: 50018091 | D47: 46054 | E47: CX | F47: 6 | H47: OR 92
B48: XYLESTESIN 100 MG SPRAY | C48: 50020182 | D48: 46661 | E48: UN | F48: 1 | H48: OR 92
B49: FLUMAZENIL 0,1 MG | C49: BF-002/25 | D49: 46266 | E49: CX | F49: 1 | H49: OR 92
B50: PRPOFOL 10 MG | C50: A0H0702A | D50: 46327 | E50: CX | F50: 6 | H50: OR 92
B51: PREDI-MEDROL 40 MG | C51: 2504525 | D51: 46419 | E51: CX | F51: 5 | H51: OR 92
B52: PAMERGAN 25 MG | C52: 50028182 | D52: 46508 | E52: CX | F52: 1 | H52: OR 92
B53: FUROSEMIDA 10 MG | C53: 25050480 | D53: 46508 | E53: CX | F53: 1 | H53: OR 92
B54: SUGAMADEX SODICO 100 MG | C54: AS1250245A | D54: 46478 | E54: CX | F54: 4 | H54: OR 92
B55: ETILEFRIL 10 MG | C55: 2448216 | D55: 46357 | E55: CX | F55: 3 | H55: OR 92
B56: ENCRISE 1 ML | C56: 40709684 | D56: 46296 | E56: CX | F56: 2 | H56: OR 92
B57: ADENOSINA 3 MG | C57: BC-013/24M | D57: 46296 | E57: CX | F57: 1 | H57: OR 92
B58: TROMETAMOL CETOROLACO 30 MG | C58: BH-007/24 | D58: 46235 | E58: CX | F58: 1 | H58: OR 92
B59: NORMASTIG 0,5 MG | C59: 2523019H | D59: 46508 | E59: CX | F59: 1 | H59: OR 92
B60: SUCCITRAT 100 MG | C60: 24070177 | D60: 46174 | E60: CX | F60: 1 | H60: OR 92
B61: CLORIDRATO DE NALOXONA 0,4 MG | C61: BA-006/24 | D61: 46204 | E61: CX | F61: 1 | H61: OR 92
B62: CITRATO DE FENTANILA 50 MCG | C62: AS-047/25M | D62: 46447 | E62: CX | F62: 1 | H62: OR 92
B63: FENILEFRIN 10 MG | C63: 50014479 | D63: 46143 | E63: CX | F63: 1 | H63: OR 92
B64: PARINEX 5 ML | C64: U027/25 | D64: 46266 | E64: CX | F64: 1 | H64: OR 92
B65: SULFATO DE TERBUTALINA 0,5 MG | C65: AV-002/25 | D65: 46447 | E65: CX | F65: 1 | H65: OR 92
B66: CLORIDRATO DE ONDANSETRONA 2 MG | C66: 25030150 | D66: 46447 | E66: CX | F66: 1 | H66: OR 92
B67: ACIDO TRANEXAMICO 50 MG | C67: BD-015/25 | D67: 46388 | E67: CX | F67: 1 | H67: OR 92
B68: UNIFEDRINE 50 MG | C68: 2432348.A | D68: 46235 | E68: CX | F68: 1 | H68: OR 92
B69: ETOMIDATO 2 MG | C69: 50024334 | D69: 46419 | E69: CX | F69: 2 | H69: OR 92
B70: KETAMIN NP 50 MG | C70: 50025872 | D70: 46447 | E70: CX | F70: 1 | H70: OR 92
B71: NUBAIN 10 MG | C71: 50024506 | D71: 46692 | E71: CX | F71: 1 | H71: OR 92
B72: ATROFARMA 0,25 MG | C72: AT24L030 C-7/1 | D72: 46296 | E72: CX | F72: 1 | H72: OR 92
B73: FOSFATO DISSODICO DE DEXAMETASONA 4 MG | C73: DX25B025 C-7/1 | D73: 46388 | E73: CX | F73: 1 | H73: OR 92
B74: DIFENIDRIN 50 MG | C74: 50025174 | D74: 46784 | E74: CX | F74: 1 | H74: OR 92
B75: CLORIDRATO DE AMIODARONA 50 MG | C75: AD-027/24 | D75: 46296 | E75: CX | F75: 1 | H75: OR 92
B76: AMINOFILINA 24 MG | C76: E-008/24M | D76: 46143 | E76: CX | F76: 2 | H76: OR 92
B77: CLONIDIN 150 MCG | C77: 50023052 | D77: 46357 | E77: CX | F77: 1 | H77: RR 16
B78: SUCCINATO SÓDICO DE HIDROCORTISONA 500 MG | C78: 25060122 | D78: 46508 | E78: CX | F78: 1 | H78: RR 16
B79: MIDAZOLAM 5 MG | C79: AP-025/25 | D79: 46419 | E79: CX | F79: 1 | H79: RR 16
B80: CEFAZOLINA SÓDICA 1 G | C80: 10577 | D80: 46388 | E80: CX | F80: 1 | H80: RR 16
B81: SEVOFLURANO SOL INA 250ML | C81: 10466 | D81: 46327 | E81: UN | F81: 22 | H81: SC 03
